__init__.py
otm_bi.py
otm_bi_sti.py
otm_uni.py
simple.py
sti.py
SQLAlchemyExample-0.1.45.dist-info/LICENSE
SQLAlchemyExample-0.1.45.dist-info/METADATA
SQLAlchemyExample-0.1.45.dist-info/WHEEL
SQLAlchemyExample-0.1.45.dist-info/top_level.txt
SQLAlchemyExample-0.1.45.dist-info/RECORD
