Metadata-Version: 2.1
Name: SQLAlchemyExample
Version: 0.1.45
Summary: Exploring SQLAlchemy
Author-email: Hendrik du Toit <hendrik@brightedge.co.za>
License: MIT License
Project-URL: Changelog, https://github.com/hendrikdutoit/SQLAlchemyExample/enhancement/master/CHANGES.md
Project-URL: Homepage, https://github.com/hendrikdutoit/SQLAlchemyExample
Classifier: Development Status :: 5 - Production/Stable
Classifier: Intended Audience :: Developers
Classifier: Topic :: Software Development
Classifier: Topic :: Database
Classifier: License :: OSI Approved :: MIT License
Classifier: Programming Language :: Python :: 3.8
Classifier: Programming Language :: Python :: 3.9
Classifier: Programming Language :: Python :: 3.10
Classifier: Programming Language :: Python :: 3.11
Requires-Python: <=12.0,>=3.10
License-File: LICENSE
Requires-Dist: mysql-connector-python
Requires-Dist: sqlalchemy <2.0.0
Requires-Dist: sqlalchemy-utils
Provides-Extra: dev
Requires-Dist: git-it ; extra == 'dev'
Requires-Dist: Pygments ; extra == 'dev'
Requires-Dist: pytest ; extra == 'dev'
Requires-Dist: pytest-cov ; extra == 'dev'
Requires-Dist: rstcheck ; extra == 'dev'
Requires-Dist: uvicorn ; extra == 'dev'
